lab2/src/descarga.v
module bateria(carga,warn);
    input [3:0] carga;
    output warn;
    assign warn = (~carga[0]&~carga[1])&(~carga[2]&~carga[3]);
endmodule


module bateria2(carga1,carga2,warn1,warn2);
    input [3:0] carga1,carga2;
    output warn1, warn2;
    bateria bateria1(.carga(carga1), .warn(warn1));
    bateria bateria2(.carga(carga2), .warn(warn2));
endmodule

lab2/descarga_tb.v
`include "descarga.v"
`timescale 1ps/1ps

module warntb();
    reg [3:0] carga1_tb, carga2_tb;
    wire warn1_tb, warn2_tb;

    bateria2 uut(
        .carga1(carga1_tb),
        .carga2(carga2_tb),
        .warn1(warn1_tb),
        .warn2(warn2_tb)
    );
    
    initial begin
        carga1_tb = 4'b0000;
        carga2_tb = 4'b0000;
        #1;
        carga1_tb = 4'b0001;
        carga2_tb = 4'b0001;
        #1;
        carga1_tb = 4'b0010;
        carga2_tb = 4'b0010;
        #1;
        carga1_tb = 4'b0011;
        carga2_tb = 4'b0011;
        #1;
        carga1_tb = 4'b0100;
        carga2_tb = 4'b0100;
        #1;
        carga1_tb = 4'b0101;
        carga2_tb = 4'b0101;
        #1;
        carga1_tb = 4'b0110;
        carga2_tb = 4'b0110;
        #1;
        carga1_tb = 4'b0111;
        carga2_tb = 4'b0111;
        #1;
        carga1_tb = 4'b1000;
        carga2_tb = 4'b1000;
        #1;
        carga1_tb = 4'b1001;
        carga2_tb = 4'b1001;
        #1;
        carga1_tb = 4'b1010;
        carga2_tb = 4'b1010;
        #1;
        carga1_tb = 4'b1011;
        carga2_tb = 4'b1011;
        #1;
        carga1_tb = 4'b1100;
        carga2_tb = 4'b1100;
        #1;
        carga1_tb = 4'b1101;
        carga2_tb = 4'b1101;
        #1;
        carga1_tb = 4'b1110;
        carga2_tb = 4'b1110;
        #1;
        carga1_tb = 4'b1111;
        carga2_tb = 4'b1111;
        #1;
    end

    initial begin: TEST_CASE
        $dumpfile("descarga_tb.vcd");
        $dumpvars(-1, uut);
        #20 $finish; 
        
    end
endmodule

lab2/build/descarga_tb.vcd
$date
	Wed Dec 18 22:39:28 2024
$end
$version
	Icarus Verilog
$end
$timescale
	1ps
$end
$scope module warntb $end
$scope module uut $end
$var wire 4 ! carga1 [3:0] $end
$var wire 4 " carga2 [3:0] $end
$var wire 1 # warn2 $end
$var wire 1 $ warn1 $end
$scope module bateria1 $end
$var wire 4 % carga [3:0] $end
$var wire 1 $ warn $end
$upscope $end
$scope module bateria2 $end
$var wire 4 & carga [3:0] $end
$var wire 1 # warn $end
$upscope $end
$upscope $end
$upscope $end
$enddefinitions $end
$comment Show the parameter values. $end
$dumpall
$end
#0
$dumpvars
b0 &
b0 %
1$
1#
b0 "
b0 !
$end
#1
0#
0$
b1 "
b1 &
b1 !
b1 %
#2
b10 "
b10 &
b10 !
b10 %
#3
b11 "
b11 &
b11 !
b11 %
#4
b100 "
b100 &
b100 !
b100 %
#5
b101 "
b101 &
b101 !
b101 %
#6
b110 "
b110 &
b110 !
b110 %
#7
b111 "
b111 &
b111 !
b111 %
#8
b1000 "
b1000 &
b1000 !
b1000 %
#9
b1001 "
b1001 &
b1001 !
b1001 %
#10
b1010 "
b1010 &
b1010 !
b1010 %
#11
b1011 "
b1011 &
b1011 !
b1011 %
#12
b1100 "
b1100 &
b1100 !
b1100 %
#13
b1101 "
b1101 &
b1101 !
b1101 %
#14
b1110 "
b1110 &
b1110 !
b1110 %
#15
b1111 "
b1111 &
b1111 !
b1111 %
