lab2/sumador.v
module adder(a,b,cin,cout,sum);
    input   a,b,cin;
    output  cout,sum;
    assign sum  = cin^(a^b);  
    assign cout = (cin&(a|b))|(a&b);
endmodule

module adder4b(A,B,Cout,sum4);
    input [3:0] A,B;
    output [3:0] sum4; 
    output Cout;
    wire [2:0] ctem;

    adder bit1(A[0], B[0],  0     , ctem[0], sum4[0]);
    adder bit2(A[1], B[1], ctem[0], ctem[1], sum4[1]);
    adder bit3(A[2], B[2], ctem[1], ctem[2], sum4[2]);
    adder bit4(A[3], B[3], ctem[2], Cout, sum4[3]);
endmodule

lab2/restador.v
`include "sumador.v"

module restador(suma,cout_co);
    input [3:0] suma;
    output cout_co;
    adder4b com2(suma,4'b1100, cout_co,);
endmodule

lab2/nivelcarga.v
`include "restador.v"

module nivelcarga(A,B,green,yellow,critical);
    input [3:0] A,B;
    output green, yellow, critical;
    wire [3:0] suma;
    wire co_s, co_r;
    wire in;
    assign in = 1'b1;

    adder4b    sumaAB(A,B,co_s, suma);
    restador resta(suma,co_r);

    assign green    = in&co_s;
    assign yellow   = in&~co_s&co_r;
    assign critical = in&~co_s&~co_r; 

endmodule

lab2/src/nivelcarga_tb.v
`include "nivelcarga.v"

`timescale 1ps/1ps

module nivelcarga_tb();
    reg [3:0] A_tb, B_tb;
    wire green_tb, yellow_tb, critical_tb;

    nivelcarga uut(
        .A(A_tb),
        .B(B_tb),
        .green(green_tb),
        .yellow(yellow_tb),
        .critical(critical_tb)
    );
    
    initial begin
        A_tb = 4'b0000;
        B_tb = 4'b0000;
        #1;
        A_tb = 4'b0001;
        B_tb = 4'b0001;
        #1;
        A_tb = 4'b0010;
        B_tb = 4'b0010;
        #1;
        A_tb = 4'b0011;
        B_tb = 4'b0011;
        #1;
        A_tb = 4'b0100;
        B_tb = 4'b0100;
        #1;
        A_tb = 4'b0101;
        B_tb = 4'b0101;
        #1;
        A_tb = 4'b0110;
        B_tb = 4'b0110;
        #1;
        A_tb = 4'b0111;
        B_tb = 4'b0111;
        #1;
        A_tb = 4'b1000;
        B_tb = 4'b1000;
        #1;
        A_tb = 4'b1001;
        B_tb = 4'b1001;
        #1;
        A_tb = 4'b1010;
        B_tb = 4'b1010;
        #1;
        A_tb = 4'b1011;
        B_tb = 4'b1011;
        #1;
        A_tb = 4'b1100;
        B_tb = 4'b1100;
        #1;
        A_tb = 4'b1101;
        B_tb = 4'b1101;
        #1;
        A_tb = 4'b1110;
        B_tb = 4'b1110;
        #1;
        A_tb = 4'b1111;
        B_tb = 4'b1111;
        #1;
    end

    initial begin: TEST_CASE
        $dumpfile("nivelcarga_tb.vcd");
        $dumpvars(-1, uut);
        #20 $finish; 
        
    end
endmodule

lab2/build/nivelcarga_tb.vcd
$date
	Wed Dec  4 22:46:06 2024
$end
$version
	Icarus Verilog
$end
$timescale
	1ps
$end
$scope module nivelcarga_tb $end
$scope module uut $end
$var wire 4 ! A [3:0] $end
$var wire 4 " B [3:0] $end
$var wire 1 # critical $end
$var wire 1 $ green $end
$var wire 1 % in $end
$var wire 1 & yellow $end
$var wire 4 ' suma [3:0] $end
$var wire 1 ( co_s $end
$var wire 1 ) co_r $end
$scope module resta $end
$var wire 4 * suma [3:0] $end
$var wire 1 ) cout_co $end
$scope module com2 $end
$var wire 4 + B [3:0] $end
$var wire 4 , sum4 [3:0] $end
$var wire 3 - ctem [2:0] $end
$var wire 1 ) Cout $end
$var wire 4 . A [3:0] $end
$scope module bit1 $end
$var wire 1 / a $end
$var wire 1 0 b $end
$var wire 1 1 cin $end
$var wire 1 2 cout $end
$var wire 1 3 sum $end
$upscope $end
$scope module bit2 $end
$var wire 1 4 a $end
$var wire 1 5 b $end
$var wire 1 6 cin $end
$var wire 1 7 cout $end
$var wire 1 8 sum $end
$upscope $end
$scope module bit3 $end
$var wire 1 9 a $end
$var wire 1 : b $end
$var wire 1 ; cin $end
$var wire 1 < cout $end
$var wire 1 = sum $end
$upscope $end
$scope module bit4 $end
$var wire 1 > a $end
$var wire 1 ? b $end
$var wire 1 @ cin $end
$var wire 1 ) cout $end
$var wire 1 A sum $end
$upscope $end
$upscope $end
$upscope $end
$scope module sumaAB $end
$var wire 4 B A [3:0] $end
$var wire 4 C B [3:0] $end
$var wire 4 D sum4 [3:0] $end
$var wire 3 E ctem [2:0] $end
$var wire 1 ( Cout $end
$scope module bit1 $end
$var wire 1 F a $end
$var wire 1 G b $end
$var wire 1 H cin $end
$var wire 1 I cout $end
$var wire 1 J sum $end
$upscope $end
$scope module bit2 $end
$var wire 1 K a $end
$var wire 1 L b $end
$var wire 1 M cin $end
$var wire 1 N cout $end
$var wire 1 O sum $end
$upscope $end
$scope module bit3 $end
$var wire 1 P a $end
$var wire 1 Q b $end
$var wire 1 R cin $end
$var wire 1 S cout $end
$var wire 1 T sum $end
$upscope $end
$scope module bit4 $end
$var wire 1 U a $end
$var wire 1 V b $end
$var wire 1 W cin $end
$var wire 1 ( cout $end
$var wire 1 X sum $end
$upscope $end
$upscope $end
$upscope $end
$upscope $end
$enddefinitions $end
$comment Show the parameter values. $end
$dumpall
$end
#0
$dumpvars
0X
0W
0V
0U
0T
0S
0R
0Q
0P
0O
0N
0M
0L
0K
0J
0I
0H
0G
0F
b0 E
b0 D
b0 C
b0 B
1A
0@
1?
0>
1=
0<
0;
1:
09
08
07
06
05
04
03
02
01
00
0/
b0 .
b0 -
b1100 ,
b1100 +
b0 *
0)
0(
b0 '
0&
1%
0$
1#
b0 "
b0 !
$end
#1
b1110 ,
18
14
b10 '
b10 *
b10 .
b10 D
1O
1M
b1 E
1I
1G
1F
b1 "
b1 C
b1 !
b1 B
#2
0#
1&
1)
0A
1@
08
b0 ,
0=
b100 -
1<
04
19
0O
b100 '
b100 *
b100 .
b100 D
1T
0M
1R
0I
b10 E
1N
0G
1L
0F
1K
b10 "
b10 C
b10 !
b10 B
#3
b10 ,
18
14
b110 '
b110 *
b110 .
b110 D
1O
1M
b11 E
1I
1G
1F
b11 "
b11 C
b11 !
b11 B
#4
0@
1=
b0 -
0<
08
b100 ,
0A
09
04
0T
1>
0O
0R
b1000 '
b1000 *
b1000 .
b1000 D
1X
0M
0N
1W
0I
b100 E
1S
0G
0L
1Q
0F
0K
1P
b100 "
b100 C
b100 !
b100 B
#5
b110 ,
18
14
b1010 '
b1010 *
b1010 .
b1010 D
1O
1M
b101 E
1I
1G
1F
b101 "
b101 C
b101 !
b101 B
#6
1A
1@
08
b1000 ,
0=
b100 -
1<
04
19
0O
b1100 '
b1100 *
b1100 .
b1100 D
1T
0M
1R
0I
b110 E
1N
0G
1L
0F
1K
b110 "
b110 C
b110 !
b110 B
#7
b1010 ,
18
14
b1110 '
b1110 *
b1110 .
b1110 D
1O
1M
b111 E
1I
1G
1F
b111 "
b111 C
b111 !
b111 B
#8
0)
0@
1=
b0 -
0<
1A
b1100 ,
08
09
0>
04
0T
0X
0&
b0 '
b0 *
b0 .
b0 D
0O
0R
0W
0M
0N
0S
1$
b0 E
0I
1(
0G
0L
0Q
1V
0F
0K
0P
1U
b1000 "
b1000 C
b1000 !
b1000 B
#9
b1110 ,
18
14
b10 '
b10 *
b10 .
b10 D
1O
1M
b1 E
1I
1G
1F
b1001 "
b1001 C
b1001 !
b1001 B
#10
1)
0A
1@
08
b0 ,
0=
b100 -
1<
04
19
0O
b100 '
b100 *
b100 .
b100 D
1T
0M
1R
0I
b10 E
1N
0G
1L
0F
1K
b1010 "
b1010 C
b1010 !
b1010 B
#11
b10 ,
18
14
b110 '
b110 *
b110 .
b110 D
1O
1M
b11 E
1I
1G
1F
b1011 "
b1011 C
b1011 !
b1011 B
#12
0@
1=
b0 -
0<
08
b100 ,
0A
09
04
0T
1>
0O
0R
b1000 '
b1000 *
b1000 .
b1000 D
1X
0M
0N
1W
0I
b100 E
1S
0G
0L
1Q
0F
0K
1P
b1100 "
b1100 C
b1100 !
b1100 B
#13
b110 ,
18
14
b1010 '
b1010 *
b1010 .
b1010 D
1O
1M
b101 E
1I
1G
1F
b1101 "
b1101 C
b1101 !
b1101 B
#14
1A
1@
08
b1000 ,
0=
b100 -
1<
04
19
0O
b1100 '
b1100 *
b1100 .
b1100 D
1T
0M
1R
0I
b110 E
1N
0G
1L
0F
1K
b1110 "
b1110 C
b1110 !
b1110 B
#15
b1010 ,
18
14
b1110 '
b1110 *
b1110 .
b1110 D
1O
1M
b111 E
1I
1G
1F
b1111 "
b1111 C
b1111 !
b1111 B
