lab2/sumador.v
module adder(a,b,cin,cout,sum);
    input   a,b,cin;
    output  cout,sum;
    assign sum  = cin^(a^b);  
    assign cout = (cin&(a|b))|(a&b);
endmodule

module adder4b(A,B,Cout,sum4);
    input [3:0] A,B;
    output [3:0] sum4; 
    output Cout;
    wire [2:0] ctem;

    adder bit1(A[0], B[0],  0     , ctem[0], sum4[0]);
    adder bit2(A[1], B[1], ctem[0], ctem[1], sum4[1]);
    adder bit3(A[2], B[2], ctem[1], ctem[2], sum4[2]);
    adder bit4(A[3], B[3], ctem[2], Cout, sum4[3]);
endmodule

lab2/src/sumador_tb.v
`include "sumador.v"
`timescale 1ps/1ps

module adder4btb();
    reg [3:0] A_tb, B_tb;
    wire Cout_tb, sum4_tb;

    adder4b uut(
        .A(A_tb),
        .B(B_tb),
        .Cout(Cout_tb),
        .sum4(sum4_tb)
    );
    
    initial begin
        A_tb = 4'b0000;
        B_tb = 4'b0000;
        #1;
        A_tb = 4'b0001;
        B_tb = 4'b0001;
        #1;
        A_tb = 4'b0010;
        B_tb = 4'b0010;
        #1;
        A_tb = 4'b0011;
        B_tb = 4'b0011;
        #1;
        A_tb = 4'b0100;
        B_tb = 4'b0100;
        #1;
        A_tb = 4'b0101;
        B_tb = 4'b0101;
        #1;
        A_tb = 4'b0110;
        B_tb = 4'b0110;
        #1;
        A_tb = 4'b0111;
        B_tb = 4'b0111;
        #1;
        A_tb = 4'b1000;
        B_tb = 4'b1000;
        #1;
        A_tb = 4'b1001;
        B_tb = 4'b1001;
        #1;
        A_tb = 4'b1010;
        B_tb = 4'b1010;
        #1;
        A_tb = 4'b1011;
        B_tb = 4'b1011;
        #1;
        A_tb = 4'b1100;
        B_tb = 4'b1100;
        #1;
        A_tb = 4'b1101;
        B_tb = 4'b1101;
        #1;
        A_tb = 4'b1110;
        B_tb = 4'b1110;
        #1;
        A_tb = 4'b1111;
        B_tb = 4'b1111;
        #1;
    end

    initial begin: TEST_CASE
        $dumpfile("sumador_tb.vcd");
        $dumpvars(-1, uut);
        #20 $finish; 
        
    end
endmodule

lab2/build/sumador_tb.vcd
$date
	Mon Dec  2 21:33:19 2024
$end
$version
	Icarus Verilog
$end
$timescale
	1ps
$end
$scope module adder4btb $end
$scope module uut $end
$var wire 4 ! A [3:0] $end
$var wire 4 " B [3:0] $end
$var wire 4 # sum4 [3:0] $end
$var wire 3 $ ctem [2:0] $end
$var wire 1 % Cout $end
$scope module bit1 $end
$var wire 1 & a $end
$var wire 1 ' b $end
$var wire 1 ( cin $end
$var wire 1 ) cout $end
$var wire 1 * sum $end
$upscope $end
$scope module bit2 $end
$var wire 1 + a $end
$var wire 1 , b $end
$var wire 1 - cin $end
$var wire 1 . cout $end
$var wire 1 / sum $end
$upscope $end
$scope module bit3 $end
$var wire 1 0 a $end
$var wire 1 1 b $end
$var wire 1 2 cin $end
$var wire 1 3 cout $end
$var wire 1 4 sum $end
$upscope $end
$scope module bit4 $end
$var wire 1 5 a $end
$var wire 1 6 b $end
$var wire 1 7 cin $end
$var wire 1 % cout $end
$var wire 1 8 sum $end
$upscope $end
$upscope $end
$upscope $end
$enddefinitions $end
$comment Show the parameter values. $end
$dumpall
$end
#0
$dumpvars
08
07
06
05
04
03
02
01
00
0/
0.
0-
0,
0+
0*
0)
0(
0'
0&
0%
b0 $
b0 #
b0 "
b0 !
$end
#1
b10 #
1/
1-
b1 $
1)
1'
1&
b1 "
b1 !
#2
0/
b100 #
14
0-
12
0)
b10 $
1.
0'
1,
0&
1+
b10 "
b10 !
#3
b110 #
1/
1-
b11 $
1)
1'
1&
b11 "
b11 !
#4
04
0/
02
b1000 #
18
0-
0.
17
0)
b100 $
13
0'
0,
11
0&
0+
10
b100 "
b100 !
#5
b1010 #
1/
1-
b101 $
1)
1'
1&
b101 "
b101 !
#6
0/
b1100 #
14
0-
12
0)
b110 $
1.
0'
1,
0&
1+
b110 "
b110 !
#7
b1110 #
1/
1-
b111 $
1)
1'
1&
b111 "
b111 !
#8
04
08
b0 #
0/
02
07
0-
0.
03
b0 $
0)
1%
0'
0,
01
16
0&
0+
00
15
b1000 "
b1000 !
#9
b10 #
1/
1-
b1 $
1)
1'
1&
b1001 "
b1001 !
#10
0/
b100 #
14
0-
12
0)
b10 $
1.
0'
1,
0&
1+
b1010 "
b1010 !
#11
b110 #
1/
1-
b11 $
1)
1'
1&
b1011 "
b1011 !
#12
04
0/
02
b1000 #
18
0-
0.
17
0)
b100 $
13
0'
0,
11
0&
0+
10
b1100 "
b1100 !
#13
b1010 #
1/
1-
b101 $
1)
1'
1&
b1101 "
b1101 !
#14
0/
b1100 #
14
0-
12
0)
b110 $
1.
0'
1,
0&
1+
b1110 "
b1110 !
#15
b1110 #
1/
1-
b111 $
1)
1'
1&
b1111 "
b1111 !
