lab3/clockdiv.v
module clockdiv #(parameter div = 16'd50000)(clin, clout);
    input clin;
    output reg clout;

    reg [15:0] count = 16'd0;

    initial begin
        clout <= 0;
    end
    always @(posedge clin) begin
        count <= count + 16'd1;
        if (count == div-1) begin
            count <= 16'd0;
            clout <= ~clout;
        end
    end

endmodule

lab3/clockdiv_tb.v
`include "clockdiv.v"
`timescale 1ns/1ns

module tb_clockdiv;
    reg clin;
    wire clout, clout2, clout3;

    clockdiv #(
        .div(16'd4)
    ) uut (             
        .clin(clin),
        .clout(clout)
    );

    clockdiv #(
        .div(16'd2)
    ) uut2 (             
        .clin(clin),
        .clout(clout2)
    );

    clockdiv #(
        .div(16'd3)
    ) uut3 (             
        .clin(clin),
        .clout(clout3)
    );

    initial begin
        clin = 0;
        forever #50 clin = ~clin;
    end

    initial begin: TEST_CASE
        $dumpfile("clockdiv_tb.vcd");
        $dumpvars(-1, uut,uut2,uut3);
        #2000 $finish;  
    end
endmodule

lab3/clockdiv_tb.vcd
$date
	Sun Feb  2 00:15:01 2025
$end
$version
	Icarus Verilog
$end
$timescale
	1ns
$end
$scope module tb_clockdiv $end
$scope module uut $end
$var wire 1 ! clin $end
$var parameter 16 " div $end
$var reg 1 # clout $end
$var reg 16 $ count [15:0] $end
$upscope $end
$upscope $end
$scope module tb_clockdiv $end
$scope module uut2 $end
$var wire 1 ! clin $end
$var parameter 16 % div $end
$var reg 1 & clout $end
$var reg 16 ' count [15:0] $end
$upscope $end
$upscope $end
$scope module tb_clockdiv $end
$scope module uut3 $end
$var wire 1 ! clin $end
$var parameter 16 ( div $end
$var reg 1 ) clout $end
$var reg 16 * count [15:0] $end
$upscope $end
$upscope $end
$enddefinitions $end
$comment Show the parameter values. $end
$dumpall
b11 (
b10 %
b100 "
$end
#0
$dumpvars
b0 *
0)
b0 '
0&
b0 $
0#
0!
$end
#50
b1 $
b1 '
b1 *
1!
#100
0!
#150
b10 *
1&
b0 '
b10 $
1!
#200
0!
#250
b11 $
b1 '
1)
b0 *
1!
#300
0!
#350
b1 *
0&
b0 '
1#
b0 $
1!
#400
0!
#450
b1 $
b1 '
b10 *
1!
#500
0!
#550
0)
b0 *
1&
b0 '
b10 $
1!
#600
0!
#650
b11 $
b1 '
b1 *
1!
#700
0!
#750
b10 *
0&
b0 '
0#
b0 $
1!
#800
0!
#850
b1 $
b1 '
1)
b0 *
1!
#900
0!
#950
b1 *
1&
b0 '
b10 $
1!
#1000
0!
#1050
b11 $
b1 '
b10 *
1!
#1100
0!
#1150
0)
b0 *
0&
b0 '
1#
b0 $
1!
#1200
0!
#1250
b1 $
b1 '
b1 *
1!
#1300
0!
#1350
b10 *
1&
b0 '
b10 $
1!
#1400
0!
#1450
b11 $
b1 '
1)
b0 *
1!
#1500
0!
#1550
b1 *
0&
b0 '
0#
b0 $
1!
#1600
0!
#1650
b1 $
b1 '
b10 *
1!
#1700
0!
#1750
0)
b0 *
1&
b0 '
b10 $
1!
#1800
0!
#1850
b11 $
b1 '
b1 *
1!
#1900
0!
#1950
b10 *
0&
b0 '
1#
b0 $
1!
#2000
0!
